odoo/addons/dms_user_role/README.rst
odoo/addons/dms_user_role/__init__.py
odoo/addons/dms_user_role/__manifest__.py
odoo/addons/dms_user_role/i18n/dms_user_role.pot
odoo/addons/dms_user_role/i18n/es.po
odoo/addons/dms_user_role/i18n/it.po
odoo/addons/dms_user_role/i18n/sv.po
odoo/addons/dms_user_role/models/__init__.py
odoo/addons/dms_user_role/models/dms_access_group.py
odoo/addons/dms_user_role/readme/CONTRIBUTORS.md
odoo/addons/dms_user_role/readme/DESCRIPTION.md
odoo/addons/dms_user_role/readme/USAGE.md
odoo/addons/dms_user_role/static/description/icon.png
odoo/addons/dms_user_role/static/description/index.html
odoo/addons/dms_user_role/tests/__init__.py
odoo/addons/dms_user_role/tests/test_dms_user_role.py
odoo/addons/dms_user_role/views/dms_access_group_views.xml
odoo_addon_dms_user_role-18.0.1.0.0.4.dist-info/METADATA
odoo_addon_dms_user_role-18.0.1.0.0.4.dist-info/WHEEL
odoo_addon_dms_user_role-18.0.1.0.0.4.dist-info/top_level.txt
odoo_addon_dms_user_role-18.0.1.0.0.4.dist-info/RECORD
